{"title":"우리 영화 볼래?","url":"https://tv.kakao.com/channel/462787/video","favicon":"https://img1.kakaocdn.net/kakaotv/services/2020/icon/icon-16.png","elements":[{"title":"<피렌체와 우피치 미술관> 예고편","contents":"<em class=\"screen_out\">재생시간 : </em>00:34","link":"https://tv.kakao.com/channel/462787/cliplink/447436456?act=clip","retrieved":1718353429796,"image":"https://img1.kakaocdn.net/thumb/C320x180.fjpg.q75/?fname=http%3A%2F%2Fthumb.kakaocdn.net%2Fdna%2Fkamp%2Fsource%2Frvfkbikaave830q5fj1ggzj6s%2Fthumbs%2Fthumb.jpg%3Fcredential%3DTuMuFGKUIcirOSjFzOpncbomGFEIdZWK%26expires%3D33275260863%26signature%3D%252BcqnoJQlhwm4B3bNYos3uegApTw%253D%26ts%3D1718352063"},{"title":"<피렌체와 우피치 미술관> 예고편","contents":"<em class=\"screen_out\">재생시간 : </em>01:55","link":"https://tv.kakao.com/channel/462787/cliplink/447436443?act=clip","retrieved":1718353429797,"image":"https://img1.kakaocdn.net/thumb/C320x180.fjpg.q75/?fname=http%3A%2F%2Fthumb.kakaocdn.net%2Fdna%2Fkamp%2Fsource%2Frv3rc8x19d9nb7ngybcbw1xj8%2Fthumbs%2Fthumb.jpg%3Fcredential%3DTuMuFGKUIcirOSjFzOpncbomGFEIdZWK%26expires%3D33275260827%26signature%3DoN%252BXggm7%252B%252F2wzPfTV9MnNFOP5Vc%253D%26ts%3D1718352027"},{"title":"<극장판 도라에몽: 진구의 지구 교향곡> 티저 예고편","contents":"<em class=\"screen_out\">재생시간 : </em>00:30","link":"https://tv.kakao.com/channel/462787/cliplink/447434603?act=clip","retrieved":1718349524340,"image":"https://img1.kakaocdn.net/thumb/C320x180.fjpg.q75/?fname=http%3A%2F%2Fimg1.kakaocdn.net%2Fkakaotv%2FKAKAOACCOUNT%2F1713249511%2Fthumb%2F20240614155012"},{"title":"<언럭키 로맨스> 메인 예고편","contents":"<em class=\"screen_out\">재생시간 : </em>01:25","link":"https://tv.kakao.com/channel/462787/cliplink/447432197?act=clip","retrieved":1718342352393,"image":"https://img1.kakaocdn.net/thumb/C320x180.fjpg.q75/?fname=https%3A%2F%2Fthumb.kakaocdn.net%2Fdna%2Fkamp%2Fsource%2Frvfjk57sv0vi42c7rn9wfsyku%2Fthumbs%2Fthumb.jpg%3Fcredential%3DTuMuFGKUIcirOSjFzOpncbomGFEIdZWK%26expires%3D33275249884%26signature%3DtZTCO8urT79l%252FcqO9zRoCASr55k%253D%26ts%3D1718341084"},{"title":"<블러디 이스케이프: 지옥의 도주극> 런칭 예고편","contents":"<em class=\"screen_out\">재생시간 : </em>00:29","link":"https://tv.kakao.com/channel/462787/cliplink/447432076?act=clip","retrieved":1718342352393,"image":"https://img1.kakaocdn.net/thumb/C320x180.fjpg.q75/?fname=https%3A%2F%2Fthumb.kakaocdn.net%2Fdna%2Fkamp%2Fsource%2Frvjnmiuljyckfa3mrwvovnyli%2Fthumbs%2Fthumb.jpg%3Fcredential%3DTuMuFGKUIcirOSjFzOpncbomGFEIdZWK%26expires%3D33275249535%26signature%3Dbz2KXkIcz2vR1J78J5VkpwkDYbU%253D%26ts%3D1718340735"},{"title":"<슈퍼배드 4> 한국 예고편","contents":"<em class=\"screen_out\">재생시간 : </em>01:30","link":"https://tv.kakao.com/channel/462787/cliplink/447431715?act=clip","retrieved":1718342352394,"image":"https://img1.kakaocdn.net/thumb/C320x180.fjpg.q75/?fname=http%3A%2F%2Fthumb.kakaocdn.net%2Fdna%2Fkamp%2Fsource%2Frv1zin6qevhe3iqn4ks6wh1eu%2Fthumbs%2Fthumb.jpg%3Fcredential%3DTuMuFGKUIcirOSjFzOpncbomGFEIdZWK%26expires%3D33275248242%26signature%3D5zS%252F2JDfFYy3It6y0H5TQYb70X4%253D%26ts%3D1718339442"},{"title":"<우리와 상관없이> 메인 예고편","contents":"<em class=\"screen_out\">재생시간 : </em>00:59","link":"https://tv.kakao.com/channel/462787/cliplink/447431630?act=clip","retrieved":1718342352394,"image":"https://img1.kakaocdn.net/thumb/C320x180.fjpg.q75/?fname=http%3A%2F%2Fthumb.kakaocdn.net%2Fdna%2Fkamp%2Fsource%2Frvtr0wjur8aioq4raj5qer0zk%2Fthumbs%2Fthumb.jpg%3Fcredential%3DTuMuFGKUIcirOSjFzOpncbomGFEIdZWK%26expires%3D33275248037%26signature%3DLgTjfa89z5RiVcNdZEw8zhCl%252Fnc%253D%26ts%3D1718339237"},{"title":"<러브 라이즈 블리딩> 30초 예고편","contents":"<em class=\"screen_out\">재생시간 : </em>00:30","link":"https://tv.kakao.com/channel/462787/cliplink/447428603?act=clip","retrieved":1718332554192,"image":"https://img1.kakaocdn.net/thumb/C320x180.fjpg.q75/?fname=http%3A%2F%2Fimg1.kakaocdn.net%2Fkakaotv%2FKAKAOACCOUNT%2F630673302%2Fthumb%2F20240614133137"},{"title":"<생츄어리> 추천 영상","contents":"<em class=\"screen_out\">재생시간 : </em>04:20","link":"https://tv.kakao.com/channel/462787/cliplink/447428545?act=clip","retrieved":1718332554193,"image":"https://img1.kakaocdn.net/thumb/C320x180.fjpg.q75/?fname=http%3A%2F%2Fthumb.kakaocdn.net%2Fdna%2Fkamp%2Fsource%2Frvr45l6bluf98iz0ftu7dp776%2Fthumbs%2Fthumb.jpg%3Fcredential%3DTuMuFGKUIcirOSjFzOpncbomGFEIdZWK%26expires%3D33275238128%26signature%3DeMEx%252FoK3M7TMs4ViEjBx0xaGpGM%253D%26ts%3D1718329328"},{"title":"<북극백화점의 안내원> 'Gift' 뮤직비디오","contents":"<em class=\"screen_out\">재생시간 : </em>01:44","link":"https://tv.kakao.com/channel/462787/cliplink/447411821?act=clip","retrieved":1718263110470,"image":"https://img1.kakaocdn.net/thumb/C320x180.fjpg.q75/?fname=https%3A%2F%2Fthumb.kakaocdn.net%2Fdna%2Fkamp%2Fsource%2Frvujudo5p4jasjpyzj5jcrp3m%2Fthumbs%2Fthumb.jpg%3Fcredential%3DTuMuFGKUIcirOSjFzOpncbomGFEIdZWK%26expires%3D33275169248%26signature%3Do0XsKwhsRs%252FO13k9IevU5lUSv%252BA%253D%26ts%3D1718260448"},{"title":"<콰이어트 플레이스: 첫째 날> 출구 없음 30초 영상","contents":"<em class=\"screen_out\">재생시간 : </em>00:30","link":"https://tv.kakao.com/channel/462787/cliplink/447410190?act=clip","retrieved":1718256006608,"image":"https://img1.kakaocdn.net/thumb/C320x180.fjpg.q75/?fname=http%3A%2F%2Fthumb.kakaocdn.net%2Fdna%2Fkamp%2Fsource%2Frvoed5zq1pwocwhhqiwbrfvw1%2Fthumbs%2Fthumb.jpg%3Fcredential%3DTuMuFGKUIcirOSjFzOpncbomGFEIdZWK%26expires%3D33275164111%26signature%3DzeoNua591yU47M0fhggQi1ddtko%253D%26ts%3D1718255311"},{"title":"<콰이어트 플레이스: 첫째 날> 첫째 날 생존 가이드 영상","contents":"<em class=\"screen_out\">재생시간 : </em>01:48","link":"https://tv.kakao.com/channel/462787/cliplink/447410174?act=clip","retrieved":1718256006612,"image":"https://img1.kakaocdn.net/thumb/C320x180.fjpg.q75/?fname=http%3A%2F%2Fthumb.kakaocdn.net%2Fdna%2Fkamp%2Fsource%2Frvaa2w2qs4dr3yfhhruwkce8l%2Fthumbs%2Fthumb.jpg%3Fcredential%3DTuMuFGKUIcirOSjFzOpncbomGFEIdZWK%26expires%3D33275164087%26signature%3DS0tgkI%252Fi3FXcL%252FrQsYohk7oJIp0%253D%26ts%3D1718255287"},{"title":"<탈출: 프로젝트 사일런스> 메인 예고편","contents":"<em class=\"screen_out\">재생시간 : </em>01:19","link":"https://tv.kakao.com/channel/462787/cliplink/447410068?act=clip","retrieved":1718256006622,"image":"https://img1.kakaocdn.net/thumb/C320x180.fjpg.q75/?fname=http%3A%2F%2Fthumb.kakaocdn.net%2Fdna%2Fkamp%2Fsource%2Frvk1d7rphdsnsm8vey4i027d1%2Fthumbs%2Fthumb.jpg%3Fcredential%3DTuMuFGKUIcirOSjFzOpncbomGFEIdZWK%26expires%3D33275163810%26signature%3DTjolOyBiT7geYuabqtdDtT5LCMo%253D%26ts%3D1718255010"},{"title":"<포춘 오브 워> 예고편","contents":"<em class=\"screen_out\">재생시간 : </em>01:19","link":"https://tv.kakao.com/channel/462787/cliplink/447406024?act=clip","retrieved":1718246082225,"image":"https://img1.kakaocdn.net/thumb/C320x180.fjpg.q75/?fname=http%3A%2F%2Fthumb.kakaocdn.net%2Fdna%2Fkamp%2Fsource%2Frv2lbxfeek8fxo30rkr2qthtj%2Fthumbs%2Fthumb.jpg%3Fcredential%3DTuMuFGKUIcirOSjFzOpncbomGFEIdZWK%26expires%3D33275151784%26signature%3DPkgTVaE%252Bg0g3ThPR8ABLuAVtiek%253D%26ts%3D1718242984"},{"title":"<보통의 우주는 찬란함을 꿈꾸는가?> 30초 예고편","contents":"<em class=\"screen_out\">재생시간 : </em>00:30","link":"https://tv.kakao.com/channel/462787/cliplink/447405986?act=clip","retrieved":1718246082225,"image":"https://img1.kakaocdn.net/thumb/C320x180.fjpg.q75/?fname=http%3A%2F%2Fthumb.kakaocdn.net%2Fdna%2Fkamp%2Fsource%2Frv965i7yrv7451ctl11npknef%2Fthumbs%2Fthumb.jpg%3Fcredential%3DTuMuFGKUIcirOSjFzOpncbomGFEIdZWK%26expires%3D33275151615%26signature%3DLy8s7raANynQIxaeE6PqmLZ6n2s%253D%26ts%3D1718242815"},{"title":"<인사이드 아웃 2> 파이널 예고편","contents":"<em class=\"screen_out\">재생시간 : </em>01:28","link":"https://tv.kakao.com/channel/462787/cliplink/447389969?act=clip","retrieved":1718180680207,"image":"https://img1.kakaocdn.net/thumb/C320x180.fjpg.q75/?fname=http%3A%2F%2Fthumb.kakaocdn.net%2Fdna%2Fkamp%2Fsource%2Frvk7nhyf0jcngqtoyjf11utwb%2Fthumbs%2Fthumb.jpg%3Fcredential%3DTuMuFGKUIcirOSjFzOpncbomGFEIdZWK%26expires%3D33275086676%26signature%3DWm2m%252FFdsD5qDo8fzAuctizUrHrw%253D%26ts%3D1718177876"},{"title":"<인사이드 아웃 2> 예매 오픈 완료 영상","contents":"<em class=\"screen_out\">재생시간 : </em>00:20","link":"https://tv.kakao.com/channel/462787/cliplink/447389933?act=clip","retrieved":1718180680220,"image":"https://img1.kakaocdn.net/thumb/C320x180.fjpg.q75/?fname=http%3A%2F%2Fthumb.kakaocdn.net%2Fdna%2Fkamp%2Fsource%2Frvdtqzg4ua8ojv4rtesdvxmhv%2Fthumbs%2Fthumb.jpg%3Fcredential%3DTuMuFGKUIcirOSjFzOpncbomGFEIdZWK%26expires%3D33275086605%26signature%3Dy6WCsa5LcCcf8iaDKPJ%252BGT9wn8A%253D%26ts%3D1718177805"},{"title":"<탈주> 캐릭터 예고편","contents":"<em class=\"screen_out\">재생시간 : </em>00:58","link":"https://tv.kakao.com/channel/462787/cliplink/447387885?act=clip","retrieved":1718173617060,"image":"https://img1.kakaocdn.net/thumb/C320x180.fjpg.q75/?fname=https%3A%2F%2Fthumb.kakaocdn.net%2Fdna%2Fkamp%2Fsource%2Frv2ibxmvxpxbp9mbubkj0anuh%2Fthumbs%2Fthumb.jpg%3Fcredential%3DTuMuFGKUIcirOSjFzOpncbomGFEIdZWK%26expires%3D33275080946%26signature%3D47RDHN6SF4hoixZ3Wevq0edn6ds%253D%26ts%3D1718172146"},{"title":"<하이재킹> 공중정보통 영상","contents":"<em class=\"screen_out\">재생시간 : </em>01:55","link":"https://tv.kakao.com/channel/462787/cliplink/447386815?act=clip","retrieved":1718169572411,"image":"https://img1.kakaocdn.net/thumb/C320x180.fjpg.q75/?fname=https%3A%2F%2Fthumb.kakaocdn.net%2Fdna%2Fkamp%2Fsource%2Frvmzw5ur56lmjw65iy6t7yav8%2Fthumbs%2Fthumb.jpg%3Fcredential%3DTuMuFGKUIcirOSjFzOpncbomGFEIdZWK%26expires%3D33275077837%26signature%3DsGhsA9uI2T2m0aICmgIBcpngX8g%253D%26ts%3D1718169037"},{"title":"<마거리트의 정리> 30초 예고편","contents":"<em class=\"screen_out\">재생시간 : </em>00:30","link":"https://tv.kakao.com/channel/462787/cliplink/447386692?act=clip","retrieved":1718169572412,"image":"https://img1.kakaocdn.net/thumb/C320x180.fjpg.q75/?fname=http%3A%2F%2Fimg1.kakaocdn.net%2Fkakaotv%2FKAKAOACCOUNT%2F1820224848%2Fthumb%2F20240612140540"},{"title":"<사일런트 나잇> 메인 예고편","contents":"<em class=\"screen_out\">재생시간 : </em>01:30","link":"https://tv.kakao.com/channel/462787/cliplink/447386657?act=clip","retrieved":1718169572414,"image":"https://img1.kakaocdn.net/thumb/C240x140.fjpg.q75/?fname=https%3A%2F%2Fthumb.kakaocdn.net%2Fdna%2Fkamp%2Fsource%2Frv2xaikakzjsbxcraqgal68ib%2Fthumbs%2Fthumb.jpg%3Fcredential%3DTuMuFGKUIcirOSjFzOpncbomGFEIdZWK%26expires%3D33275077424%26signature%3DVP%252F04s9IjypnGY717CKMEgPInZM%253D%26ts%3D1718168624"},{"title":"<만천과해> 메인 예고편","contents":"<em class=\"screen_out\">재생시간 : </em>01:09","link":"https://tv.kakao.com/channel/462787/cliplink/447386596?act=clip","retrieved":1718169572415,"image":"https://img1.kakaocdn.net/thumb/C240x140.fjpg.q75/?fname=https%3A%2F%2Fthumb.kakaocdn.net%2Fdna%2Fkamp%2Fsource%2Frvtmadpazcnx419huh6b4z246%2Fthumbs%2Fthumb.jpg%3Fcredential%3DTuMuFGKUIcirOSjFzOpncbomGFEIdZWK%26expires%3D33275077262%26signature%3DPlqdpnxc45VqOBCAe%252F1c%252FlIphR4%253D%26ts%3D1718168462"},{"title":"<프리실라> 브이로그 영상","contents":"<em class=\"screen_out\">재생시간 : </em>00:59","link":"https://tv.kakao.com/channel/462787/cliplink/447386500?act=clip","retrieved":1718169572415,"image":"https://img1.kakaocdn.net/thumb/C240x140.fjpg.q75/?fname=http%3A%2F%2Fthumb.kakaocdn.net%2Fdna%2Fkamp%2Fsource%2Frvhf2fqq7kn73022aysqt0poz%2Fthumbs%2Fthumb.jpg%3Fcredential%3DTuMuFGKUIcirOSjFzOpncbomGFEIdZWK%26expires%3D33275077050%26signature%3DywATd%252BMNd0OZ2Fj0PtBw3mGEM74%253D%26ts%3D1718168250"},{"title":"<몽키맨> 액션 GOAT 몽키맨 도착 영상","contents":"<em class=\"screen_out\">재생시간 : </em>00:30","link":"https://tv.kakao.com/channel/462787/cliplink/447367130?act=clip","retrieved":1718094322479,"image":"https://img1.kakaocdn.net/thumb/C240x140.fjpg.q75/?fname=https%3A%2F%2Fthumb.kakaocdn.net%2Fdna%2Fkamp%2Fsource%2Frvfmab2vgnde66dmd405xyneo%2Fthumbs%2Fthumb.jpg%3Fcredential%3DTuMuFGKUIcirOSjFzOpncbomGFEIdZWK%26expires%3D33275000884%26signature%3DXjvGplcko9lwpdL%252F4TT%252BfM5UNbw%253D%26ts%3D1718092084"},{"title":"<불륜: 위험한 본능> 예고편","contents":"<em class=\"screen_out\">재생시간 : </em>01:39","link":"https://tv.kakao.com/channel/462787/cliplink/447367089?act=clip","retrieved":1718094322481,"image":"https://img1.kakaocdn.net/thumb/C240x140.fjpg.q75/?fname=http%3A%2F%2Fthumb.kakaocdn.net%2Fdna%2Fkamp%2Fsource%2Frvm5arrhncd0ep7vaqq83gqyh%2Fthumbs%2Fthumb.jpg%3Fcredential%3DTuMuFGKUIcirOSjFzOpncbomGFEIdZWK%26expires%3D33275000739%26signature%3DU7iD%252FItlO55Be43TYr%252FpWsqLU%252BY%253D%26ts%3D1718091939"},{"title":"<에이리언: 로물루스> 메인 예고편","contents":"<em class=\"screen_out\">재생시간 : </em>02:00","link":"https://tv.kakao.com/channel/462787/cliplink/447363376?act=clip","retrieved":1718083197508,"image":"https://img1.kakaocdn.net/thumb/C240x140.fjpg.q75/?fname=http%3A%2F%2Fthumb.kakaocdn.net%2Fdna%2Fkamp%2Fsource%2Frv8tsgj3jozknihlu0yev6d7b%2Fthumbs%2Fthumb.jpg%3Fcredential%3DTuMuFGKUIcirOSjFzOpncbomGFEIdZWK%26expires%3D33274991126%26signature%3Dh6fVm7bj%252FOBvPLUJmFDBq3IEjxI%253D%26ts%3D1718082326&mode=watermark&wm_id=kakaotv_14&wm_img_type1=R240x140"},{"title":"<이다 : 영원한 사랑 이야기> 예고편","contents":"<em class=\"screen_out\">재생시간 : </em>01:00","link":"https://tv.kakao.com/channel/462787/cliplink/447362861?act=clip","retrieved":1718083197509,"image":"https://img1.kakaocdn.net/thumb/C240x140.fjpg.q75/?fname=http%3A%2F%2Fimg1.kakaocdn.net%2Fkakaotv%2FKAKAOACCOUNT%2F166087852%2Fthumb%2F20240611133830"},{"title":"<북극백화점의 안내원> V.I.A 소개영상","contents":"<em class=\"screen_out\">재생시간 : </em>00:58","link":"https://tv.kakao.com/channel/462787/cliplink/447362781?act=clip","retrieved":1718083197509,"image":"https://img1.kakaocdn.net/thumb/C240x140.fjpg.q75/?fname=http%3A%2F%2Fthumb.kakaocdn.net%2Fdna%2Fkamp%2Fsource%2Frv7jl27xopw3eg773x1y4o5lz%2Fthumbs%2Fthumb.jpg%3Fcredential%3DTuMuFGKUIcirOSjFzOpncbomGFEIdZWK%26expires%3D33274989293%26signature%3DZ3e%252BIesRVNq3MOnkldcMD5GotPU%253D%26ts%3D1718080493"},{"title":"<1초 앞, 1초 뒤> '떠나자! 랜선 교토 여행' 영상","contents":"<em class=\"screen_out\">재생시간 : </em>00:27","link":"https://tv.kakao.com/channel/462787/cliplink/447343707?act=clip","retrieved":1718007955683,"image":"https://img1.kakaocdn.net/thumb/C240x140.fjpg.q75/?fname=http%3A%2F%2Fthumb.kakaocdn.net%2Fdna%2Fkamp%2Fsource%2Frvegkmg7j7kt7agrbhgkjvcgf%2Fthumbs%2Fthumb.jpg%3Fcredential%3DTuMuFGKUIcirOSjFzOpncbomGFEIdZWK%26expires%3D33274915983%26signature%3D60JvK9RrJlI%252BGQPncFaUvvnZJjc%253D%26ts%3D1718007183"},{"title":"<북극백화점의 안내원> 백화점 이용 안내 영상","contents":"<em class=\"screen_out\">재생시간 : </em>01:11","link":"https://tv.kakao.com/channel/462787/cliplink/447343484?act=clip","retrieved":1718007955684,"image":"https://img1.kakaocdn.net/thumb/C240x140.fjpg.q75/?fname=http%3A%2F%2Fthumb.kakaocdn.net%2Fdna%2Fkamp%2Fsource%2Frvumiqjk1s920bq1b8y946at8%2Fthumbs%2Fthumb.jpg%3Fcredential%3DTuMuFGKUIcirOSjFzOpncbomGFEIdZWK%26expires%3D33274915372%26signature%3D7qOmKlJqNv4MpRQoiQ69qqjLAa8%253D%26ts%3D1718006572"},{"title":"<핸섬가이즈> 2차 예고편","contents":"<em class=\"screen_out\">재생시간 : </em>01:47","link":"https://tv.kakao.com/channel/462787/cliplink/447341670?act=clip","retrieved":1718003923583,"image":"https://img1.kakaocdn.net/thumb/C240x140.fjpg.q75/?fname=http%3A%2F%2Fthumb.kakaocdn.net%2Fdna%2Fkamp%2Fsource%2Frvgaw3a3jkodpjestikghueuk%2Fthumbs%2Fthumb.jpg%3Fcredential%3DTuMuFGKUIcirOSjFzOpncbomGFEIdZWK%26expires%3D33274910103%26signature%3D1s0DzuZlLe4tJGYcDbpBUuXibaY%253D%26ts%3D1718001303"},{"title":"<태풍 클럽> 30초 예고편","contents":"<em class=\"screen_out\">재생시간 : </em>00:30","link":"https://tv.kakao.com/channel/462787/cliplink/447339483?act=clip","retrieved":1717996782715,"image":"https://img1.kakaocdn.net/thumb/C240x140.fjpg.q75/?fname=http%3A%2F%2Fthumb.kakaocdn.net%2Fdna%2Fkamp%2Fsource%2Frvqcuei4p7byblnoxg4jf42fm%2Fthumbs%2Fthumb.jpg%3Fcredential%3DTuMuFGKUIcirOSjFzOpncbomGFEIdZWK%26expires%3D33274903943%26signature%3DOv0uxRz6BAeCrVGkl49HDI9%252BMLw%253D%26ts%3D1717995143"},{"title":"<원한의 정사> 예고편","contents":"<em class=\"screen_out\">재생시간 : </em>00:50","link":"https://tv.kakao.com/channel/462787/cliplink/447339432?act=clip","retrieved":1717996782716,"image":"https://img1.kakaocdn.net/thumb/C240x140.fjpg.q75/?fname=https%3A%2F%2Fthumb.kakaocdn.net%2Fdna%2Fkamp%2Fsource%2Frvrve0di6cn6k8begol5znes2%2Fthumbs%2Fthumb.jpg%3Fcredential%3DTuMuFGKUIcirOSjFzOpncbomGFEIdZWK%26expires%3D33274903804%26signature%3DYaSzXGXEUS2qN06Pz99BObySJCY%253D%26ts%3D1717995004"},{"title":"<아찔한 유혹> 예고편","contents":"<em class=\"screen_out\">재생시간 : </em>01:09","link":"https://tv.kakao.com/channel/462787/cliplink/447339406?act=clip","retrieved":1717996782717,"image":"https://img1.kakaocdn.net/thumb/C240x140.fjpg.q75/?fname=https%3A%2F%2Fthumb.kakaocdn.net%2Fdna%2Fkamp%2Fsource%2Frvgywc2hw527a62bfiajgdddw%2Fthumbs%2Fthumb.jpg%3Fcredential%3DTuMuFGKUIcirOSjFzOpncbomGFEIdZWK%26expires%3D33274903673%26signature%3DO1M1PMEAchhZ2wdtms4SLSAC9Ro%253D%26ts%3D1717994873"},{"title":"<신부의 유혹> 예고편","contents":"<em class=\"screen_out\">재생시간 : </em>00:52","link":"https://tv.kakao.com/channel/462787/cliplink/447339372?act=clip","retrieved":1717996782730,"image":"https://img1.kakaocdn.net/thumb/C240x140.fjpg.q75/?fname=http%3A%2F%2Fthumb.kakaocdn.net%2Fdna%2Fkamp%2Fsource%2Frvve3n57n1xi4u1blbjwagpdd%2Fthumbs%2Fthumb.jpg%3Fcredential%3DTuMuFGKUIcirOSjFzOpncbomGFEIdZWK%26expires%3D33274903515%26signature%3D8VraKwUnC1okahP9fz1RQVMznTc%253D%26ts%3D1717994715"},{"title":"<명탐정 코난: 100만 달러의 펜타그램> 슈퍼 티저 예고편","contents":"<em class=\"screen_out\">재생시간 : </em>00:30","link":"https://tv.kakao.com/channel/462787/cliplink/447339330?act=clip","retrieved":1717996782731,"image":"https://img1.kakaocdn.net/thumb/C240x140.fjpg.q75/?fname=http%3A%2F%2Fthumb.kakaocdn.net%2Fdna%2Fkamp%2Fsource%2Frvzddeltur1cdr4gs8nc076pg%2Fthumbs%2Fthumb.jpg%3Fcredential%3DTuMuFGKUIcirOSjFzOpncbomGFEIdZWK%26expires%3D33274903364%26signature%3DkiRSNilWUnKHfrV%252F7hiwWxVR1pg%253D%26ts%3D1717994564"},{"title":"<존 오브 인터레스트> 메이킹 영상","contents":"<em class=\"screen_out\">재생시간 : </em>02:03","link":"https://tv.kakao.com/channel/462787/cliplink/447335413?act=clip","retrieved":1717987028310,"image":"https://img1.kakaocdn.net/thumb/C240x140.fjpg.q75/?fname=https%3A%2F%2Fthumb.kakaocdn.net%2Fdna%2Fkamp%2Fsource%2Frvd67ou1qr9um70x4d4lihkli%2Fthumbs%2Fthumb.jpg%3Fcredential%3DTuMuFGKUIcirOSjFzOpncbomGFEIdZWK%26expires%3D33274892934%26signature%3DHnXCPvRn1XcAJyJRMFs0nSKeKEo%253D%26ts%3D1717984134"},{"title":"<파랑> 메인 예고편","contents":"<em class=\"screen_out\">재생시간 : </em>01:09","link":"https://tv.kakao.com/channel/462787/cliplink/447335298?act=clip","retrieved":1717987028311,"image":"https://img1.kakaocdn.net/thumb/C240x140.fjpg.q75/?fname=http%3A%2F%2Fthumb.kakaocdn.net%2Fdna%2Fkamp%2Fsource%2Frv3puxg8m8bvzau46w8zizzqq%2Fthumbs%2Fthumb.jpg%3Fcredential%3DTuMuFGKUIcirOSjFzOpncbomGFEIdZWK%26expires%3D33274892608%26signature%3DLVBTyYJDGJg%252BJ%252FMFv8IA3Fex4Ks%253D%26ts%3D1717983808"},{"title":"<콰이어트 플레이스: 첫째 날> 침묵의 도시 30초 예고편","contents":"<em class=\"screen_out\">재생시간 : </em>00:30","link":"https://tv.kakao.com/channel/462787/cliplink/447272175?act=clip","retrieved":1717727776758,"image":"https://img1.kakaocdn.net/thumb/C240x140.fjpg.q75/?fname=http%3A%2F%2Fthumb.kakaocdn.net%2Fdna%2Fkamp%2Fsource%2Frvmc1j4vj5vmn5jz24l9lh9uu%2Fthumbs%2Fthumb.jpg%3Fcredential%3DTuMuFGKUIcirOSjFzOpncbomGFEIdZWK%26expires%3D33274635659%26signature%3DiA2rJXMMQbnae49DmwU9mP8twnI%253D%26ts%3D1717726859"},{"title":"<콰이어트 플레이스: 첫째 날> 첫째 날은 너무 어려워 30초 예고편","contents":"<em class=\"screen_out\">재생시간 : </em>00:30","link":"https://tv.kakao.com/channel/462787/cliplink/447272153?act=clip","retrieved":1717727776759,"image":"https://img1.kakaocdn.net/thumb/C240x140.fjpg.q75/?fname=https%3A%2F%2Fthumb.kakaocdn.net%2Fdna%2Fkamp%2Fsource%2Frv3wgrobvmwc325n9jc4255jj%2Fthumbs%2Fthumb.jpg%3Fcredential%3DTuMuFGKUIcirOSjFzOpncbomGFEIdZWK%26expires%3D33274635624%26signature%3Djq11E46XC6nj5nnnsNipXMwWjuo%253D%26ts%3D1717726824"}]}